kafka_slurm_agent/__init__.py
kafka_slurm_agent/cluster_agent.py
kafka_slurm_agent/command.py
kafka_slurm_agent/config_module.py
kafka_slurm_agent/kafka_modules.py
kafka_slurm_agent/monitor_agent.py
kafka_slurm_agent/runner.py
kafka_slurm_agent/worker_agent.py
kafka_slurm_agent-1.3.7.data/data/cluster_agent
kafka_slurm_agent-1.3.7.data/data/kafkaslurm_cfg.py__
kafka_slurm_agent-1.3.7.data/data/monitor_agent
kafka_slurm_agent-1.3.7.data/data/worker_agent
kafka_slurm_agent-1.3.7.dist-info/licenses/LICENSE
kafka_slurm_agent-1.3.7.dist-info/METADATA
kafka_slurm_agent-1.3.7.dist-info/WHEEL
kafka_slurm_agent-1.3.7.dist-info/entry_points.txt
kafka_slurm_agent-1.3.7.dist-info/top_level.txt
kafka_slurm_agent-1.3.7.dist-info/RECORD
