Metadata-Version: 2.4
Name: kafka_slurm_agent
Version: 1.3.7
Summary: The Kafka Slurm Agent is a distributed computing and stream processing engine that can be used to run python code acrossmultiple SLURM managed HPC clusters or individual workstations.It uses Kafka to asynchronously communicate with agents installed on clusters and workstations.It contains a monitoring tool with a Web JSON API and a job submitter.It is a pure Python implementation using faust stream processing
Home-page: https://github.com/prubach/kafka-slurm-agent
Author: Paweł Rubach
Author-email: pawel.rubach@gmail.com
Classifier: Programming Language :: Python :: 3
Classifier: Programming Language :: Python :: 3.6
Classifier: Programming Language :: Python :: 3.7
Classifier: Programming Language :: Python :: 3.8
Classifier: Programming Language :: Python :: 3.9
Classifier: Programming Language :: Python :: 3.10
Classifier: Programming Language :: Python :: 3.11
Classifier: Programming Language :: Python :: 3.12
Classifier: Programming Language :: Python :: 3.13
Classifier: License :: OSI Approved :: MIT License
Classifier: Operating System :: OS Independent
Requires-Python: >=3.6.0
License-File: LICENSE
Requires-Dist: simple-slurm
Requires-Dist: kafka-python-ng
Requires-Dist: psutil>=5.6.6
Requires-Dist: python-math
Requires-Dist: faust-streaming
Requires-Dist: werkzeug
Requires-Dist: wrapt-timeout-decorator
Dynamic: author
Dynamic: author-email
Dynamic: classifier
Dynamic: description
Dynamic: description-content-type
Dynamic: home-page
Dynamic: license-file
Dynamic: requires-dist
Dynamic: requires-python
Dynamic: summary
